stere/__init__.py
stere/browserenabled.py
stere/event_emitter.py
stere/page.py
stere/py.typed
stere/utils.py
stere/value_comparator.py
stere/areas/__init__.py
stere/areas/area.py
stere/areas/areas.py
stere/areas/repeating.py
stere/areas/repeating_area.py
stere/browser_spy/__init__.py
stere/browser_spy/fetch.py
stere/browser_spy/fetch_script.py
stere/browser_spy/xhr.py
stere/browser_spy/xhr_script.py
stere/fields/__init__.py
stere/fields/build_element.py
stere/fields/decorators.py
stere/fields/field.py
stere/fields/appium/__init__.py
stere/fields/appium/button.py
stere/fields/appium/input.py
stere/fields/generic/__init__.py
stere/fields/generic/root.py
stere/fields/generic/text.py
stere/fields/splinter/__init__.py
stere/fields/splinter/button.py
stere/fields/splinter/checkbox.py
stere/fields/splinter/clickable.py
stere/fields/splinter/dropdown.py
stere/fields/splinter/input.py
stere/fields/splinter/link.py
stere/fields/splinter/money.py
stere/fields/splinter/shadow_root.py
stere/strategy/__init__.py
stere/strategy/appium.py
stere/strategy/element_strategy.py
stere/strategy/splinter.py
stere/strategy/strategy.py
stere-0.31.0.dist-info/LICENSE
stere-0.31.0.dist-info/METADATA
stere-0.31.0.dist-info/WHEEL
stere-0.31.0.dist-info/top_level.txt
stere-0.31.0.dist-info/RECORD
