Metadata-Version: 2.1
Name: stere
Version: 0.31.0
Summary: A nice way of implementing the Page Object pattern.
Home-page: https://github.com/jsfehler/stere
Author: Joshua Fehler
Author-email: jsfehler@gmail.com
License: MIT
Platform: UNKNOWN
Classifier: Programming Language :: Python :: 3.6
Classifier: Programming Language :: Python :: 3.7
Classifier: Programming Language :: Python :: 3.8
Classifier: Programming Language :: Python :: 3.9
Classifier: License :: OSI Approved :: MIT License
Classifier: Operating System :: OS Independent
Classifier: Development Status :: 4 - Beta
License-File: LICENSE
Requires-Dist: py-moneyed (==1.0)
Provides-Extra: splinter
Requires-Dist: splinter (==0.14.0) ; extra == 'splinter'
